contextnest/__init__.py
contextnest/mcp_client.py
contextnest/mcp_logger.py
contextnest/mcp_models.py
contextnest/mcp_server.py
contextnest/server_tools.py
contextnest/micro_search/__init__.py
contextnest/micro_search/database.py
contextnest/micro_search/db_preparation.py
contextnest/micro_search/hybrid_search.py
contextnest/micro_search/insertion.py
contextnest/web_scraper/README.md
contextnest/web_scraper/__init__.py
contextnest/web_scraper/captcha_handler.py
contextnest/web_scraper/markdown_converter.py
contextnest/web_scraper/scraper.py
contextnest/web_scraper/utils.py
contextnest-0.1.2.dist-info/METADATA
contextnest-0.1.2.dist-info/WHEEL
contextnest-0.1.2.dist-info/entry_points.txt
contextnest-0.1.2.dist-info/licenses/LICENSE
contextnest-0.1.2.dist-info/RECORD
