Metadata-Version: 2.4
Name: contextnest
Version: 0.1.2
Summary: A cozy `nest` where all needed context is pre‑assembled for the LLM.
Project-URL: Homepage, https://gitlab.com/ezzeldeen1/contextnest
Project-URL: Repository, https://gitlab.com/ezzeldeen1/contextnest
Author: Ezzeldeen Mamdouh
License: MIT
License-File: LICENSE
Keywords: context,fastmcp,knowledge-base,llm,mcp
Classifier: Development Status :: 4 - Beta
Classifier: Intended Audience :: Developers
Classifier: License :: OSI Approved :: MIT License
Classifier: Programming Language :: Python :: 3.13
Requires-Python: >=3.13
Requires-Dist: beautifulsoup4>=4.14.3
Requires-Dist: duckdb>=1.4.3
Requires-Dist: fastmcp>=2.14.1
Requires-Dist: google-genai>=1.56.0
Requires-Dist: html-to-markdown>=2.15.0
Requires-Dist: langchain-text-splitters>=1.1.0
Requires-Dist: loguru>=0.7.3
Requires-Dist: lxml>=6.0.2
Requires-Dist: numpy>=2.4.0
Requires-Dist: ollama>=0.6.1
Requires-Dist: playwright-stealth>=2.0.0
Requires-Dist: playwright>=1.57.0
Requires-Dist: pyarrow>=22.0.0
Requires-Dist: semantic-text-splitter>=0.28.0
Requires-Dist: tqdm>=4.67.1
Provides-Extra: linting
Requires-Dist: ruff>=0.14.10; extra == 'linting'
Provides-Extra: unit-testing
Requires-Dist: pytest-asyncio>=1.3.0; extra == 'unit-testing'
